{
  "entries": [
    {
      "date": "2026-07-05",
      "type": "post",
      "category": "gov-subsidy",
      "title": "기초생활수급자 생계급여 신청 자격과 소득인정액 기본 개념",
      "slug": "basic-livelihood-income-standard"
    },
    {
      "date": "2026-07-06",
      "type": "post",
      "category": "youth-policy",
      "title": "청년내일저축계좌 가입 조건과 3년 만기 구조",
      "slug": "youth-naeil-savings-account-guide"
    },
    {
      "date": "2026-07-06",
      "type": "column",
      "title": "정부 지원금 공고문은 왜 이렇게 어렵게 쓰여 있을까",
      "slug": "gov-subsidy-notice-language"
    }
  ]
}
